[
  {
    "neuron_id": "20231130_LIP_7",
    "cluster_id": 7,
    "file": "spikes/unit_007.h5",
    "n_spikes": 80994
  },
  {
    "neuron_id": "20231130_LIP_8",
    "cluster_id": 8,
    "file": "spikes/unit_008.h5",
    "n_spikes": 68090
  },
  {
    "neuron_id": "20231130_LIP_10",
    "cluster_id": 10,
    "file": "spikes/unit_010.h5",
    "n_spikes": 93003
  },
  {
    "neuron_id": "20231130_LIP_12",
    "cluster_id": 12,
    "file": "spikes/unit_012.h5",
    "n_spikes": 63064
  },
  {
    "neuron_id": "20231130_LIP_13",
    "cluster_id": 13,
    "file": "spikes/unit_013.h5",
    "n_spikes": 72476
  },
  {
    "neuron_id": "20231130_LIP_15",
    "cluster_id": 15,
    "file": "spikes/unit_015.h5",
    "n_spikes": 73942
  },
  {
    "neuron_id": "20231130_LIP_17",
    "cluster_id": 17,
    "file": "spikes/unit_017.h5",
    "n_spikes": 23266
  },
  {
    "neuron_id": "20231130_LIP_18",
    "cluster_id": 18,
    "file": "spikes/unit_018.h5",
    "n_spikes": 111210
  },
  {
    "neuron_id": "20231130_LIP_20",
    "cluster_id": 20,
    "file": "spikes/unit_020.h5",
    "n_spikes": 102382
  },
  {
    "neuron_id": "20231130_LIP_21",
    "cluster_id": 21,
    "file": "spikes/unit_021.h5",
    "n_spikes": 73444
  },
  {
    "neuron_id": "20231130_LIP_22",
    "cluster_id": 22,
    "file": "spikes/unit_022.h5",
    "n_spikes": 79491
  },
  {
    "neuron_id": "20231130_LIP_24",
    "cluster_id": 24,
    "file": "spikes/unit_024.h5",
    "n_spikes": 191798
  },
  {
    "neuron_id": "20231130_LIP_25",
    "cluster_id": 25,
    "file": "spikes/unit_025.h5",
    "n_spikes": 31680
  },
  {
    "neuron_id": "20231130_LIP_26",
    "cluster_id": 26,
    "file": "spikes/unit_026.h5",
    "n_spikes": 66027
  },
  {
    "neuron_id": "20231130_LIP_27",
    "cluster_id": 27,
    "file": "spikes/unit_027.h5",
    "n_spikes": 167643
  },
  {
    "neuron_id": "20231130_LIP_29",
    "cluster_id": 29,
    "file": "spikes/unit_029.h5",
    "n_spikes": 77265
  },
  {
    "neuron_id": "20231130_LIP_30",
    "cluster_id": 30,
    "file": "spikes/unit_030.h5",
    "n_spikes": 82619
  },
  {
    "neuron_id": "20231130_LIP_31",
    "cluster_id": 31,
    "file": "spikes/unit_031.h5",
    "n_spikes": 186783
  },
  {
    "neuron_id": "20231130_LIP_32",
    "cluster_id": 32,
    "file": "spikes/unit_032.h5",
    "n_spikes": 29562
  },
  {
    "neuron_id": "20231130_LIP_33",
    "cluster_id": 33,
    "file": "spikes/unit_033.h5",
    "n_spikes": 89338
  },
  {
    "neuron_id": "20231130_LIP_35",
    "cluster_id": 35,
    "file": "spikes/unit_035.h5",
    "n_spikes": 79479
  },
  {
    "neuron_id": "20231130_LIP_37",
    "cluster_id": 37,
    "file": "spikes/unit_037.h5",
    "n_spikes": 83807
  },
  {
    "neuron_id": "20231130_LIP_38",
    "cluster_id": 38,
    "file": "spikes/unit_038.h5",
    "n_spikes": 87300
  },
  {
    "neuron_id": "20231130_LIP_39",
    "cluster_id": 39,
    "file": "spikes/unit_039.h5",
    "n_spikes": 105444
  },
  {
    "neuron_id": "20231130_LIP_40",
    "cluster_id": 40,
    "file": "spikes/unit_040.h5",
    "n_spikes": 57301
  },
  {
    "neuron_id": "20231130_LIP_41",
    "cluster_id": 41,
    "file": "spikes/unit_041.h5",
    "n_spikes": 14633
  },
  {
    "neuron_id": "20231130_LIP_42",
    "cluster_id": 42,
    "file": "spikes/unit_042.h5",
    "n_spikes": 61256
  },
  {
    "neuron_id": "20231130_LIP_43",
    "cluster_id": 43,
    "file": "spikes/unit_043.h5",
    "n_spikes": 114399
  },
  {
    "neuron_id": "20231130_LIP_44",
    "cluster_id": 44,
    "file": "spikes/unit_044.h5",
    "n_spikes": 150185
  },
  {
    "neuron_id": "20231130_LIP_45",
    "cluster_id": 45,
    "file": "spikes/unit_045.h5",
    "n_spikes": 65756
  },
  {
    "neuron_id": "20231130_LIP_46",
    "cluster_id": 46,
    "file": "spikes/unit_046.h5",
    "n_spikes": 82644
  },
  {
    "neuron_id": "20231130_LIP_47",
    "cluster_id": 47,
    "file": "spikes/unit_047.h5",
    "n_spikes": 53696
  },
  {
    "neuron_id": "20231130_LIP_48",
    "cluster_id": 48,
    "file": "spikes/unit_048.h5",
    "n_spikes": 69099
  },
  {
    "neuron_id": "20231130_LIP_49",
    "cluster_id": 49,
    "file": "spikes/unit_049.h5",
    "n_spikes": 75402
  },
  {
    "neuron_id": "20231130_LIP_50",
    "cluster_id": 50,
    "file": "spikes/unit_050.h5",
    "n_spikes": 44015
  },
  {
    "neuron_id": "20231130_LIP_51",
    "cluster_id": 51,
    "file": "spikes/unit_051.h5",
    "n_spikes": 177668
  },
  {
    "neuron_id": "20231130_LIP_52",
    "cluster_id": 52,
    "file": "spikes/unit_052.h5",
    "n_spikes": 79280
  },
  {
    "neuron_id": "20231130_LIP_53",
    "cluster_id": 53,
    "file": "spikes/unit_053.h5",
    "n_spikes": 68310
  },
  {
    "neuron_id": "20231130_LIP_54",
    "cluster_id": 54,
    "file": "spikes/unit_054.h5",
    "n_spikes": 123737
  },
  {
    "neuron_id": "20231130_LIP_56",
    "cluster_id": 56,
    "file": "spikes/unit_056.h5",
    "n_spikes": 53094
  },
  {
    "neuron_id": "20231130_LIP_58",
    "cluster_id": 58,
    "file": "spikes/unit_058.h5",
    "n_spikes": 96670
  },
  {
    "neuron_id": "20231130_LIP_62",
    "cluster_id": 62,
    "file": "spikes/unit_062.h5",
    "n_spikes": 17798
  }
]