[
  {
    "neuron_id": "20230710_FEF_3",
    "cluster_id": 3,
    "file": "spikes/unit_003.h5",
    "n_spikes": 10896
  },
  {
    "neuron_id": "20230710_FEF_7",
    "cluster_id": 7,
    "file": "spikes/unit_007.h5",
    "n_spikes": 11881
  },
  {
    "neuron_id": "20230710_FEF_10",
    "cluster_id": 10,
    "file": "spikes/unit_010.h5",
    "n_spikes": 88729
  },
  {
    "neuron_id": "20230710_FEF_13",
    "cluster_id": 13,
    "file": "spikes/unit_013.h5",
    "n_spikes": 65698
  },
  {
    "neuron_id": "20230710_FEF_14",
    "cluster_id": 14,
    "file": "spikes/unit_014.h5",
    "n_spikes": 165081
  },
  {
    "neuron_id": "20230710_FEF_15",
    "cluster_id": 15,
    "file": "spikes/unit_015.h5",
    "n_spikes": 35885
  },
  {
    "neuron_id": "20230710_FEF_16",
    "cluster_id": 16,
    "file": "spikes/unit_016.h5",
    "n_spikes": 123931
  },
  {
    "neuron_id": "20230710_FEF_17",
    "cluster_id": 17,
    "file": "spikes/unit_017.h5",
    "n_spikes": 28830
  },
  {
    "neuron_id": "20230710_FEF_19",
    "cluster_id": 19,
    "file": "spikes/unit_019.h5",
    "n_spikes": 21426
  },
  {
    "neuron_id": "20230710_FEF_23",
    "cluster_id": 23,
    "file": "spikes/unit_023.h5",
    "n_spikes": 42981
  },
  {
    "neuron_id": "20230710_FEF_24",
    "cluster_id": 24,
    "file": "spikes/unit_024.h5",
    "n_spikes": 652
  },
  {
    "neuron_id": "20230710_FEF_25",
    "cluster_id": 25,
    "file": "spikes/unit_025.h5",
    "n_spikes": 41358
  },
  {
    "neuron_id": "20230710_FEF_26",
    "cluster_id": 26,
    "file": "spikes/unit_026.h5",
    "n_spikes": 20010
  },
  {
    "neuron_id": "20230710_FEF_27",
    "cluster_id": 27,
    "file": "spikes/unit_027.h5",
    "n_spikes": 155679
  },
  {
    "neuron_id": "20230710_FEF_29",
    "cluster_id": 29,
    "file": "spikes/unit_029.h5",
    "n_spikes": 54660
  },
  {
    "neuron_id": "20230710_FEF_30",
    "cluster_id": 30,
    "file": "spikes/unit_030.h5",
    "n_spikes": 54449
  },
  {
    "neuron_id": "20230710_FEF_32",
    "cluster_id": 32,
    "file": "spikes/unit_032.h5",
    "n_spikes": 2495
  },
  {
    "neuron_id": "20230710_FEF_33",
    "cluster_id": 33,
    "file": "spikes/unit_033.h5",
    "n_spikes": 42885
  },
  {
    "neuron_id": "20230710_FEF_34",
    "cluster_id": 34,
    "file": "spikes/unit_034.h5",
    "n_spikes": 38335
  },
  {
    "neuron_id": "20230710_FEF_35",
    "cluster_id": 35,
    "file": "spikes/unit_035.h5",
    "n_spikes": 27379
  },
  {
    "neuron_id": "20230710_FEF_38",
    "cluster_id": 38,
    "file": "spikes/unit_038.h5",
    "n_spikes": 24106
  },
  {
    "neuron_id": "20230710_FEF_41",
    "cluster_id": 41,
    "file": "spikes/unit_041.h5",
    "n_spikes": 40567
  },
  {
    "neuron_id": "20230710_FEF_44",
    "cluster_id": 44,
    "file": "spikes/unit_044.h5",
    "n_spikes": 1995
  },
  {
    "neuron_id": "20230710_FEF_45",
    "cluster_id": 45,
    "file": "spikes/unit_045.h5",
    "n_spikes": 42896
  },
  {
    "neuron_id": "20230710_FEF_47",
    "cluster_id": 47,
    "file": "spikes/unit_047.h5",
    "n_spikes": 3393
  },
  {
    "neuron_id": "20230710_FEF_49",
    "cluster_id": 49,
    "file": "spikes/unit_049.h5",
    "n_spikes": 52415
  },
  {
    "neuron_id": "20230710_FEF_50",
    "cluster_id": 50,
    "file": "spikes/unit_050.h5",
    "n_spikes": 34269
  },
  {
    "neuron_id": "20230710_FEF_52",
    "cluster_id": 52,
    "file": "spikes/unit_052.h5",
    "n_spikes": 9426
  },
  {
    "neuron_id": "20230710_FEF_53",
    "cluster_id": 53,
    "file": "spikes/unit_053.h5",
    "n_spikes": 8218
  },
  {
    "neuron_id": "20230710_FEF_55",
    "cluster_id": 55,
    "file": "spikes/unit_055.h5",
    "n_spikes": 22470
  },
  {
    "neuron_id": "20230710_FEF_56",
    "cluster_id": 56,
    "file": "spikes/unit_056.h5",
    "n_spikes": 19238
  },
  {
    "neuron_id": "20230710_FEF_57",
    "cluster_id": 57,
    "file": "spikes/unit_057.h5",
    "n_spikes": 3083
  },
  {
    "neuron_id": "20230710_FEF_62",
    "cluster_id": 62,
    "file": "spikes/unit_062.h5",
    "n_spikes": 6880
  },
  {
    "neuron_id": "20230710_FEF_65",
    "cluster_id": 65,
    "file": "spikes/unit_065.h5",
    "n_spikes": 48087
  },
  {
    "neuron_id": "20230710_FEF_66",
    "cluster_id": 66,
    "file": "spikes/unit_066.h5",
    "n_spikes": 28208
  },
  {
    "neuron_id": "20230710_FEF_67",
    "cluster_id": 67,
    "file": "spikes/unit_067.h5",
    "n_spikes": 65534
  },
  {
    "neuron_id": "20230710_FEF_68",
    "cluster_id": 68,
    "file": "spikes/unit_068.h5",
    "n_spikes": 26641
  },
  {
    "neuron_id": "20230710_FEF_69",
    "cluster_id": 69,
    "file": "spikes/unit_069.h5",
    "n_spikes": 74897
  },
  {
    "neuron_id": "20230710_FEF_70",
    "cluster_id": 70,
    "file": "spikes/unit_070.h5",
    "n_spikes": 127439
  },
  {
    "neuron_id": "20230710_FEF_71",
    "cluster_id": 71,
    "file": "spikes/unit_071.h5",
    "n_spikes": 29547
  },
  {
    "neuron_id": "20230710_FEF_72",
    "cluster_id": 72,
    "file": "spikes/unit_072.h5",
    "n_spikes": 25564
  },
  {
    "neuron_id": "20230710_FEF_73",
    "cluster_id": 73,
    "file": "spikes/unit_073.h5",
    "n_spikes": 37433
  },
  {
    "neuron_id": "20230710_FEF_75",
    "cluster_id": 75,
    "file": "spikes/unit_075.h5",
    "n_spikes": 48839
  },
  {
    "neuron_id": "20230710_FEF_76",
    "cluster_id": 76,
    "file": "spikes/unit_076.h5",
    "n_spikes": 7495
  },
  {
    "neuron_id": "20230710_FEF_77",
    "cluster_id": 77,
    "file": "spikes/unit_077.h5",
    "n_spikes": 18357
  },
  {
    "neuron_id": "20230710_FEF_78",
    "cluster_id": 78,
    "file": "spikes/unit_078.h5",
    "n_spikes": 17576
  },
  {
    "neuron_id": "20230710_FEF_79",
    "cluster_id": 79,
    "file": "spikes/unit_079.h5",
    "n_spikes": 11075
  },
  {
    "neuron_id": "20230710_FEF_80",
    "cluster_id": 80,
    "file": "spikes/unit_080.h5",
    "n_spikes": 7096
  },
  {
    "neuron_id": "20230710_FEF_81",
    "cluster_id": 81,
    "file": "spikes/unit_081.h5",
    "n_spikes": 29999
  },
  {
    "neuron_id": "20230710_FEF_85",
    "cluster_id": 85,
    "file": "spikes/unit_085.h5",
    "n_spikes": 89964
  },
  {
    "neuron_id": "20230710_FEF_87",
    "cluster_id": 87,
    "file": "spikes/unit_087.h5",
    "n_spikes": 2821
  },
  {
    "neuron_id": "20230710_FEF_89",
    "cluster_id": 89,
    "file": "spikes/unit_089.h5",
    "n_spikes": 6228
  },
  {
    "neuron_id": "20230710_FEF_90",
    "cluster_id": 90,
    "file": "spikes/unit_090.h5",
    "n_spikes": 1017
  },
  {
    "neuron_id": "20230710_FEF_91",
    "cluster_id": 91,
    "file": "spikes/unit_091.h5",
    "n_spikes": 3607
  },
  {
    "neuron_id": "20230710_FEF_94",
    "cluster_id": 94,
    "file": "spikes/unit_094.h5",
    "n_spikes": 23058
  },
  {
    "neuron_id": "20230710_FEF_95",
    "cluster_id": 95,
    "file": "spikes/unit_095.h5",
    "n_spikes": 2199
  },
  {
    "neuron_id": "20230710_FEF_96",
    "cluster_id": 96,
    "file": "spikes/unit_096.h5",
    "n_spikes": 3014
  },
  {
    "neuron_id": "20230710_FEF_98",
    "cluster_id": 98,
    "file": "spikes/unit_098.h5",
    "n_spikes": 3167
  },
  {
    "neuron_id": "20230710_FEF_100",
    "cluster_id": 100,
    "file": "spikes/unit_100.h5",
    "n_spikes": 1315
  },
  {
    "neuron_id": "20230710_FEF_103",
    "cluster_id": 103,
    "file": "spikes/unit_103.h5",
    "n_spikes": 838
  },
  {
    "neuron_id": "20230710_FEF_107",
    "cluster_id": 107,
    "file": "spikes/unit_107.h5",
    "n_spikes": 42210
  },
  {
    "neuron_id": "20230710_FEF_110",
    "cluster_id": 110,
    "file": "spikes/unit_110.h5",
    "n_spikes": 821
  },
  {
    "neuron_id": "20230710_FEF_111",
    "cluster_id": 111,
    "file": "spikes/unit_111.h5",
    "n_spikes": 21299
  },
  {
    "neuron_id": "20230710_FEF_122",
    "cluster_id": 122,
    "file": "spikes/unit_122.h5",
    "n_spikes": 24038
  },
  {
    "neuron_id": "20230710_FEF_125",
    "cluster_id": 125,
    "file": "spikes/unit_125.h5",
    "n_spikes": 26653
  },
  {
    "neuron_id": "20230710_FEF_153",
    "cluster_id": 153,
    "file": "spikes/unit_153.h5",
    "n_spikes": 38809
  }
]